knot_keystore/__init__.py
knot_keystore/__meta__.py
knot_keystore/cli.py
knot_keystore/knot.py
knot_keystore/archive/__init__.py
knot_keystore/archive/azure.py
knot_keystore/archive/base.py
knot_keystore/archive/local.py
knot_keystore-0.1.0.dist-info/LICENSE
knot_keystore-0.1.0.dist-info/METADATA
knot_keystore-0.1.0.dist-info/WHEEL
knot_keystore-0.1.0.dist-info/entry_points.txt
knot_keystore-0.1.0.dist-info/top_level.txt
knot_keystore-0.1.0.dist-info/RECORD
