Metadata-Version: 2.1
Name: knot-keystore
Version: 0.1.0
Summary: A tool for safely archiving knot dnssec key material to azure.
Home-page: https://github.com/wolcomm/knot-keystore
Author: Ben Maddison
Author-email: benm@workonline.africa
License: MIT
Download-URL: https://github.com/wolcomm/knot-keystore/0.1.0
Platform: UNKNOWN
Classifier: Development Status :: 3 - Alpha
Classifier: Environment :: Console
Classifier: Intended Audience :: System Administrators
Classifier: Intended Audience :: Telecommunications Industry
Classifier: License :: OSI Approved :: MIT License
Classifier: Operating System :: POSIX
Classifier: Programming Language :: Python :: 3
Classifier: Topic :: Internet :: Name Service (DNS)
Classifier: Topic :: System :: Archiving :: Backup
Requires-Python: >=3.6, <4.0
Requires-Dist: adal (<2.0,>=1.2.1)
Requires-Dist: azure-keyvault (<2.0,>=1.1.0)
Requires-Dist: azure-storage-blob (<3.0,>=2.0.1)
Requires-Dist: cryptography (<3.0,>=2.7)
Requires-Dist: libknot (>=2.8.1)
Requires-Dist: PyYAML (<6.0,>=5.1)
